<?xml version="1.0" encoding="UTF-8"?>
<WebElementEntity>
   <description></description>
   <name>ButtonSaveAdd</name>
   <tag></tag>
   <elementGuidId>d950101b-98e7-460c-a1f8-f4b25652ee73</elementGuidId>
   <selectorCollection>
      <entry>
         <key>XPATH</key>
         <value>//span[text()='${variable}']

</value>
      </entry>
      <entry>
         <key>BASIC</key>
         <value></value>
      </entry>
   </selectorCollection>
   <selectorMethod>XPATH</selectorMethod>
   <useRalativeImagePath>false</useRalativeImagePath>
</WebElementEntity>
