<?xml version="1.0" encoding="UTF-8"?>
<WebElementEntity>
   <description></description>
   <name>Message Text</name>
   <tag></tag>
   <elementGuidId>34fd335a-0dc9-4b9e-a082-f5712cc9c713</elementGuidId>
   <selectorCollection>
      <entry>
         <key>XPATH</key>
         <value>//div[text()=&quot;${text}&quot;]</value>
      </entry>
   </selectorCollection>
   <selectorMethod>XPATH</selectorMethod>
   <smartLocatorEnabled>false</smartLocatorEnabled>
   <useRalativeImagePath>false</useRalativeImagePath>
</WebElementEntity>
