<?xml version="1.0" encoding="UTF-8"?>
<WebElementEntity>
   <description></description>
   <name>input_Login_txtUsername</name>
   <tag></tag>
   <elementGuidId>599e5c8c-e9ad-46d9-a5a3-a733d185feb1</elementGuidId>
   <selectorCollection>
      <entry>
         <key>XPATH</key>
         <value>//input[@id='txtUsername']</value>
      </entry>
      <entry>
         <key>CSS</key>
         <value>#txtUsername</value>
      </entry>
   </selectorCollection>
   <selectorMethod>XPATH</selectorMethod>
   <useRalativeImagePath>true</useRalativeImagePath>
   <webElementProperties>
      <isSelected>false</isSelected>
      <matchCondition>equals</matchCondition>
      <name>tag</name>
      <type>Main</type>
      <value>input</value>
      <webElementGuid>5bf9382d-87c0-45be-b44c-6712903cc83c</webElementGuid>
   </webElementProperties>
   <webElementProperties>
      <isSelected>true</isSelected>
      <matchCondition>equals</matchCondition>
      <name>type</name>
      <type>Main</type>
      <value>text</value>
      <webElementGuid>27ef467f-5376-4c10-b080-bad1e349c85c</webElementGuid>
   </webElementProperties>
   <webElementProperties>
      <isSelected>false</isSelected>
      <matchCondition>equals</matchCondition>
      <name>size</name>
      <type>Main</type>
      <value>20</value>
      <webElementGuid>772d360f-2fb5-428e-aea6-b513e1d06f3d</webElementGuid>
   </webElementProperties>
   <webElementProperties>
      <isSelected>false</isSelected>
      <matchCondition>equals</matchCondition>
      <name>autocomplete</name>
      <type>Main</type>
      <value>off</value>
      <webElementGuid>9bcd0308-0d9b-4d17-be1e-bb39816ffbca</webElementGuid>
   </webElementProperties>
   <webElementProperties>
      <isSelected>true</isSelected>
      <matchCondition>equals</matchCondition>
      <name>id</name>
      <type>Main</type>
      <value>txtUsername</value>
      <webElementGuid>34070769-9cec-4390-b47e-597e647fd124</webElementGuid>
   </webElementProperties>
   <webElementProperties>
      <isSelected>true</isSelected>
      <matchCondition>equals</matchCondition>
      <name>name</name>
      <type>Main</type>
      <value>txtUsername</value>
      <webElementGuid>fcfa304f-a51f-4d3b-bec4-ea74995355ee</webElementGuid>
   </webElementProperties>
   <webElementProperties>
      <isSelected>false</isSelected>
      <matchCondition>equals</matchCondition>
      <name>class</name>
      <type>Main</type>
      <value> x-form-text x-form-field x-textfield-icon-input x-form-focus</value>
      <webElementGuid>51a40b09-9d2c-49b0-82d5-49b3113dd35c</webElementGuid>
   </webElementProperties>
   <webElementProperties>
      <isSelected>false</isSelected>
      <matchCondition>equals</matchCondition>
      <name>xpath</name>
      <type>Main</type>
      <value>id(&quot;txtUsername&quot;)</value>
      <webElementGuid>d58d53ca-ae8c-4238-981c-f52d7702e4ef</webElementGuid>
   </webElementProperties>
   <webElementXpaths>
      <isSelected>true</isSelected>
      <matchCondition>equals</matchCondition>
      <name>xpath:attributes</name>
      <type>Main</type>
      <value>//input[@id='txtUsername']</value>
      <webElementGuid>b774570b-b702-4a22-9be8-946d0132b917</webElementGuid>
   </webElementXpaths>
   <webElementXpaths>
      <isSelected>false</isSelected>
      <matchCondition>equals</matchCondition>
      <name>xpath:idRelative</name>
      <type>Main</type>
      <value>//div[@id='ext-gen50']/input</value>
      <webElementGuid>77332261-05c0-4ac3-aa82-711329dd8cc0</webElementGuid>
   </webElementXpaths>
   <webElementXpaths>
      <isSelected>false</isSelected>
      <matchCondition>equals</matchCondition>
      <name>xpath:position</name>
      <type>Main</type>
      <value>//input</value>
      <webElementGuid>3195be6c-52d5-43a9-91de-a5d7a63cb2ef</webElementGuid>
   </webElementXpaths>
   <webElementXpaths>
      <isSelected>false</isSelected>
      <matchCondition>equals</matchCondition>
      <name>xpath:customAttributes</name>
      <type>Main</type>
      <value>//input[@type = 'text' and @id = 'txtUsername' and @name = 'txtUsername']</value>
      <webElementGuid>7af7e001-89ec-4fe7-8088-4464a7db6486</webElementGuid>
   </webElementXpaths>
</WebElementEntity>
