<?xml version="1.0" encoding="UTF-8"?>
<WebElementEntity>
   <description></description>
   <name>Input4</name>
   <tag></tag>
   <elementGuidId>80fc3427-d787-4853-ae61-0459038c9406</elementGuidId>
   <selectorCollection>
      <entry>
         <key>BASIC</key>
      </entry>
      <entry>
         <key>XPATH</key>
         <value>(//span[text()='Field of Condition:' or text()='Field of Condition']//ancestor::fieldset[@class=&quot;x-fieldset fieldset x-fieldset-default&quot;]//child::input)[4]</value>
      </entry>
   </selectorCollection>
   <selectorMethod>XPATH</selectorMethod>
   <useRalativeImagePath>false</useRalativeImagePath>
</WebElementEntity>
