<?xml version="1.0" encoding="UTF-8"?>
<WebElementEntity>
   <description></description>
   <name>text</name>
   <tag></tag>
   <elementGuidId>655b5098-542d-495a-bddc-c40acd4db935</elementGuidId>
   <selectorCollection>
      <entry>
         <key>XPATH</key>
         <value>(//textarea[@role=&quot;textbox&quot;])[2]</value>
      </entry>
      <entry>
         <key>BASIC</key>
         <value></value>
      </entry>
   </selectorCollection>
   <selectorMethod>XPATH</selectorMethod>
   <useRalativeImagePath>false</useRalativeImagePath>
</WebElementEntity>
